LICENSE.md
MANIFEST.in
README.md
setup.py
Cassandra_Dataset_Manager.egg-info/PKG-INFO
Cassandra_Dataset_Manager.egg-info/SOURCES.txt
Cassandra_Dataset_Manager.egg-info/dependency_links.txt
Cassandra_Dataset_Manager.egg-info/entry_points.txt
Cassandra_Dataset_Manager.egg-info/requires.txt
Cassandra_Dataset_Manager.egg-info/top_level.txt
cassandra_dataset_manager.egg-info/SOURCES.txt
cdm/__init__.py
cdm/cli.py
cdm/config.py
cdm/context.py
cdm/importer.py
cdm/installer.py
cdm/models.py
cdm/notebook.py
cdm/testing.py
cdm/util.py
cdm/commands/__init__.py
cdm/commands/command.py
cdm/commands/install.py
cdm/commands/search.py
cdm/commands/stream.py
tests/__init__.py
tests/test_context.py
tests/test_importer.py
tests/test_installer.py
tests/test_search.py