Metadata-Version: 1.0
Name: cassandra-dataset-manager
Version: 0.2
Summary: Utility for quickly setting up sample datasets for Cassandra and DataStax Enterprise
Home-page: https://github.com/riptano/cdm
Author: Jon Haddad
Author-email: jon@jonhaddad.com
License: License :: OSI Approved :: Apache License
Platform: UNKNOWN
